__init__.py
social_blade_scraper/__init__.py
social_blade_scraper/fetch.py
social_blade_scraper/stats/youtube.py
social_blade_scraper-0.1.2.dist-info/METADATA
social_blade_scraper-0.1.2.dist-info/WHEEL
social_blade_scraper-0.1.2.dist-info/top_level.txt
social_blade_scraper-0.1.2.dist-info/RECORD
