Metadata-Version: 2.1
Name: social-blade-scraper
Version: 0.1.2
Summary: Social blade scraper
Home-page: https://github.com/tejmagar/social-blade-scraper
License: MIT
Classifier: Programming Language :: Python :: 3
Classifier: License :: OSI Approved :: MIT License
Classifier: Operating System :: OS Independent
Requires-Python: >=3.7
Requires-Dist: beautifulsoup4
Requires-Dist: httpx
Requires-Dist: fake-useragent
